mreg_cli/__about__.py
mreg_cli/__init__.py
mreg_cli/__main__.py
mreg_cli/_version.py
mreg_cli/cache.py
mreg_cli/cli.py
mreg_cli/config.py
mreg_cli/dirs.py
mreg_cli/errorbuilder.py
mreg_cli/exceptions.py
mreg_cli/help_formatter.py
mreg_cli/log.py
mreg_cli/main.py
mreg_cli/outputmanager.py
mreg_cli/prompt.py
mreg_cli/py.typed
mreg_cli/tags.txt
mreg_cli/tokenfile.py
mreg_cli/types.py
mreg_cli/api/__init__.py
mreg_cli/api/abstracts.py
mreg_cli/api/endpoints.py
mreg_cli/api/errors.py
mreg_cli/api/fields.py
mreg_cli/api/history.py
mreg_cli/api/models.py
mreg_cli/commands/__init__.py
mreg_cli/commands/base.py
mreg_cli/commands/cache.py
mreg_cli/commands/dhcp.py
mreg_cli/commands/group.py
mreg_cli/commands/help.py
mreg_cli/commands/host.py
mreg_cli/commands/label.py
mreg_cli/commands/logging.py
mreg_cli/commands/network.py
mreg_cli/commands/permission.py
mreg_cli/commands/policy.py
mreg_cli/commands/recording.py
mreg_cli/commands/registry.py
mreg_cli/commands/root.py
mreg_cli/commands/zone.py
mreg_cli/commands/host_submodules/__init__.py
mreg_cli/commands/host_submodules/a_aaaa.py
mreg_cli/commands/host_submodules/bacnet.py
mreg_cli/commands/host_submodules/cname.py
mreg_cli/commands/host_submodules/core.py
mreg_cli/commands/host_submodules/rr.py
mreg_cli/utilities/__init__.py
mreg_cli/utilities/api.py
mreg_cli/utilities/fs.py
mreg_cli/utilities/shared.py
mreg_cli/utilities/validators.py
mreg_cli-1.8.2.dist-info/licenses/AUTHORS
mreg_cli-1.8.2.dist-info/licenses/LICENSE
mreg_cli-1.8.2.dist-info/METADATA
mreg_cli-1.8.2.dist-info/WHEEL
mreg_cli-1.8.2.dist-info/entry_points.txt
mreg_cli-1.8.2.dist-info/top_level.txt
mreg_cli-1.8.2.dist-info/RECORD
