Metadata-Version: 2.4
Name: mreg-cli
Version: 1.8.2
Summary: MREG interactive command line client
Author: Others (see AUTHORS)
Author-email: Øyvind Kolbu <oyvind.kolbu@usit.uio.no>, Safet A <amedov@usit.uio.no>, Magnus Hirth <mhmorgan42@gmail.com>, Nico <nicolaydmohebi@gmail.com>, Marius Bakke <marius.bakke@usit.uio.no>, Fredrik Larsen <fredrik.larsen@usit.uio.no>, Paal Braathen <paal.braathen@usit.uio.no>, Nils Hiorth <nils@nls.me>, Dmytro Karpenko <dmytrok@usit.uio.no>
Maintainer-email: Terje Kvernes <terjekv@uio.no>, Øyvind Hagberg <oyvihag@uio.no>, Peder Hovdan Andresen <pederhan@uio.no>
License:                     GNU GENERAL PUBLIC LICENSE
Project-URL: Repository, https://github.com/unioslo/mreg-cli/
Keywords: mreg,cli,interactive
Classifier: Development Status :: 5 - Production/Stable
Classifier: Environment :: Console
Classifier: License :: OSI Approved :: GNU General Public License v3 (GPLv3)
Classifier: Operating System :: OS Independent
Classifier: Programming Language :: Python
Classifier: Programming Language :: Python :: 3.11
Classifier: Programming Language :: Python :: 3.12
Classifier: Programming Language :: Python :: 3.13
Requires-Python: >=3.11
License-File: LICENSE
License-File: AUTHORS
Requires-Dist: python-dateutil>=2.9.0
Requires-Dist: prompt_toolkit>=3.0.0
Requires-Dist: requests[socks]>=2.31.0
Requires-Dist: typing_extensions>=4.12.0
Requires-Dist: pydantic[email]>=2.7.1
Requires-Dist: pydantic-extra-types>=2.1.0
Requires-Dist: platformdirs>=4.3.0
Requires-Dist: diskcache>=5.6.3
Requires-Dist: pydantic-settings>=2.10.1
Requires-Dist: rich>=13.9.4
Dynamic: license-file
